{"title":"RARE","sources":{"HDG.EC":[{"starred":false,"content":"freedom rests in being able to let, to let something be in that which it rests, so rare for man to let as such [so rare for man to be free] > this freedom alone true superiority (<em>Überlegenheit</em>), doesn’t need anything below it to remain above [<em>Übermensch</em>?]","locations":{"raw":"p. 149 ","repeat":true,"list":[149],"high":149,"low":149},"source":{"display":"HDG.EC ","id":"HDG.EC","title":"Evening Conversation ","author":"HDG"},"motif":[{"name":"FREEDOM","id":"freedom","title":"FREEDOM"},{"name":"RARE","id":"rare","title":"RARE"},{"name":"ENDS OF MAN","id":"endsofman","title":"ENDS OF MAN"},{"name":"MAN","id":"man","title":"MAN"},{"name":"PAUL DE MAN","id":"pauldeman","title":"PAUL DE MAN"},{"name":"<em>ALS SICH </em>(AS SUCH)","id":"alssichassuch","title":"<em>ALS SICH </em>(AS SUCH)"},{"name":"REMAINDER / REMAINS / REMNANT","id":"remainderremainsremnant","title":"REMAINDER / REMAINS / REMNANT"}],"id":"HDG48","linkedContent":"<a href='/motif/freedom'>freedom</a> rests in being able to let, to let something be in that which it rests, so <a href='/motif/rare'>rare</a> for <a href='/disambiguate/motif?mids=endsofman,man,pauldeman'>man</a> to let as <a href='/motif/alssichassuch'>such</a> [so <a href='/motif/rare'>rare</a> for <a href='/disambiguate/motif?mids=endsofman,man,pauldeman'>man</a> to be free] > this <a href='/motif/freedom'>freedom</a> alone true superiority (<em>Überlegenheit</em>), doesn’t need anything below it to <a href='/motif/remainderremainsremnant'>remain</a> above [<em>Übermensch</em>?]"}]},"entryCount":1,"cfauthors":[]}